cmx4mlops
